annotated_dict/__init__.py
annotated_dict/mod_andi.py
annotated_dict-0.1.1.dist-info/licenses/LICENSE
annotated_dict-0.1.1.dist-info/METADATA
annotated_dict-0.1.1.dist-info/WHEEL
annotated_dict-0.1.1.dist-info/RECORD
